beaker_client-29.2-py3.13-nspkg.pth
bkr/client/__init__.py
bkr/client/command.py
bkr/client/convert.py
bkr/client/main.py
bkr/client/task_watcher.py
bkr/client/wizard.py
bkr/client/commands/__init__.py
bkr/client/commands/cmd_distro_trees_list.py
bkr/client/commands/cmd_distro_trees_verify.py
bkr/client/commands/cmd_distros_edit_version.py
bkr/client/commands/cmd_distros_list.py
bkr/client/commands/cmd_distros_tag.py
bkr/client/commands/cmd_distros_untag.py
bkr/client/commands/cmd_group_create.py
bkr/client/commands/cmd_group_list.py
bkr/client/commands/cmd_group_members.py
bkr/client/commands/cmd_group_modify.py
bkr/client/commands/cmd_harness_test.py
bkr/client/commands/cmd_job_cancel.py
bkr/client/commands/cmd_job_clone.py
bkr/client/commands/cmd_job_comment.py
bkr/client/commands/cmd_job_delete.py
bkr/client/commands/cmd_job_list.py
bkr/client/commands/cmd_job_logs.py
bkr/client/commands/cmd_job_modify.py
bkr/client/commands/cmd_job_results.py
bkr/client/commands/cmd_job_submit.py
bkr/client/commands/cmd_job_watch.py
bkr/client/commands/cmd_labcontroller_create.py
bkr/client/commands/cmd_labcontroller_list.py
bkr/client/commands/cmd_labcontroller_modify.py
bkr/client/commands/cmd_loan_grant.py
bkr/client/commands/cmd_loan_return.py
bkr/client/commands/cmd_machine_test.py
bkr/client/commands/cmd_policy_grant.py
bkr/client/commands/cmd_policy_list.py
bkr/client/commands/cmd_policy_revoke.py
bkr/client/commands/cmd_pool_add.py
bkr/client/commands/cmd_pool_create.py
bkr/client/commands/cmd_pool_delete.py
bkr/client/commands/cmd_pool_list.py
bkr/client/commands/cmd_pool_modify.py
bkr/client/commands/cmd_pool_remove.py
bkr/client/commands/cmd_pool_systems.py
bkr/client/commands/cmd_remove_account.py
bkr/client/commands/cmd_system_create.py
bkr/client/commands/cmd_system_delete.py
bkr/client/commands/cmd_system_details.py
bkr/client/commands/cmd_system_history_list.py
bkr/client/commands/cmd_system_list.py
bkr/client/commands/cmd_system_modify.py
beaker_client-29.2.dist-info/METADATA
beaker_client-29.2.dist-info/WHEEL
beaker_client-29.2.dist-info/entry_points.txt
beaker_client-29.2.dist-info/namespace_packages.txt
beaker_client-29.2.dist-info/top_level.txt
beaker_client-29.2.dist-info/RECORD
